{"expireTime":9007200928065257000,"key":"transformer-remark-markdown-html-ast-afa8b3dfe748e71b6c8826326e22bdc6-gatsby-remark-katexgatsby-remark-copy-linked-files-","val":{"type":"root","children":[{"type":"element","tagName":"h3","properties":{},"children":[{"type":"text","value":"Course Information","position":{"start":{"line":2,"column":5,"offset":5},"end":{"line":2,"column":23,"offset":23}}}],"position":{"start":{"line":2,"column":1,"offset":1},"end":{"line":2,"column":23,"offset":23}}},{"type":"text","value":"\n"},{"type":"element","tagName":"ul","properties":{},"children":[{"type":"text","value":"\n"},{"type":"element","tagName":"li","properties":{},"children":[{"type":"text","value":"Instructor: Daesung Kim (","position":{"start":{"line":3,"column":3,"offset":26},"end":{"line":3,"column":28,"offset":51}}},{"type":"element","tagName":"a","properties":{"href":"mailto:dkim3009@gatech.edu"},"children":[{"type":"text","value":"dkim3009 (at) gatech.edu","position":{"start":{"line":3,"column":29,"offset":52},"end":{"line":3,"column":53,"offset":76}}}],"position":{"start":{"line":3,"column":28,"offset":51},"end":{"line":3,"column":82,"offset":105}}},{"type":"text","value":")","position":{"start":{"line":3,"column":82,"offset":105},"end":{"line":3,"column":83,"offset":106}}}],"position":{"start":{"line":3,"column":1,"offset":24},"end":{"line":3,"column":83,"offset":106}}},{"type":"text","value":"\n"},{"type":"element","tagName":"li","properties":{},"children":[{"type":"text","value":"Office: Skiles 023","position":{"start":{"line":4,"column":3,"offset":109},"end":{"line":4,"column":21,"offset":127}}}],"position":{"start":{"line":4,"column":1,"offset":107},"end":{"line":4,"column":21,"offset":127}}},{"type":"text","value":"\n"},{"type":"element","tagName":"li","properties":{},"children":[{"type":"text","value":"Time and Place: Section A, MWF 8:25am, Howey Physics L3 / Section C, MWF 9:30am, Howey Physics L2","position":{"start":{"line":5,"column":3,"offset":130},"end":{"line":5,"column":100,"offset":227}}}],"position":{"start":{"line":5,"column":1,"offset":128},"end":{"line":5,"column":100,"offset":227}}},{"type":"text","value":"\n"},{"type":"element","tagName":"li","properties":{},"children":[{"type":"text","value":"Office Hour: TBA","position":{"start":{"line":6,"column":3,"offset":230},"end":{"line":6,"column":19,"offset":246}}}],"position":{"start":{"line":6,"column":1,"offset":228},"end":{"line":6,"column":19,"offset":246}}},{"type":"text","value":"\n"},{"type":"element","tagName":"li","properties":{},"children":[{"type":"text","value":"Textbook: Lay, Linear Algebra and its Applications, 5th Edition","position":{"start":{"line":7,"column":3,"offset":249},"end":{"line":7,"column":66,"offset":312}}}],"position":{"start":{"line":7,"column":1,"offset":247},"end":{"line":7,"column":66,"offset":312}}},{"type":"text","value":"\n"},{"type":"element","tagName":"li","properties":{},"children":[{"type":"element","tagName":"a","properties":{"href":"https://gatech.instructure.com/courses/114544/pages/common-syllabus-spring-2023"},"children":[{"type":"text","value":"Syllabus","position":{"start":{"line":8,"column":4,"offset":316},"end":{"line":8,"column":12,"offset":324}}}],"position":{"start":{"line":8,"column":3,"offset":315},"end":{"line":8,"column":94,"offset":406}}},{"type":"text","value":", ","position":{"start":{"line":8,"column":94,"offset":406},"end":{"line":8,"column":96,"offset":408}}},{"type":"element","tagName":"a","properties":{"href":"https://sbarone7.math.gatech.edu/ma1554_course_overview.pdf"},"children":[{"type":"text","value":"Course overview","position":{"start":{"line":8,"column":97,"offset":409},"end":{"line":8,"column":112,"offset":424}}}],"position":{"start":{"line":8,"column":96,"offset":408},"end":{"line":8,"column":174,"offset":486}}},{"type":"text","value":" ","position":{"start":{"line":8,"column":174,"offset":486},"end":{"line":8,"column":175,"offset":487}}}],"position":{"start":{"line":8,"column":1,"offset":313},"end":{"line":8,"column":175,"offset":487}}},{"type":"text","value":"\n"},{"type":"element","tagName":"li","properties":{},"children":[{"type":"text","value":"Textbook and Homework: ","position":{"start":{"line":9,"column":3,"offset":490},"end":{"line":9,"column":26,"offset":513}}},{"type":"element","tagName":"a","properties":{"href":"https://www.mymathlab.com"},"children":[{"type":"text","value":"https://www.mymathlab.com","position":{"start":{"line":9,"column":26,"offset":513},"end":{"line":9,"column":51,"offset":538}}}],"position":{"start":{"line":9,"column":26,"offset":513},"end":{"line":9,"column":51,"offset":538}}},{"type":"text","value":" ","position":{"start":{"line":9,"column":51,"offset":538},"end":{"line":9,"column":52,"offset":539}}}],"position":{"start":{"line":9,"column":1,"offset":488},"end":{"line":9,"column":52,"offset":539}}},{"type":"text","value":"\n"},{"type":"element","tagName":"li","properties":{},"children":[{"type":"text","value":"Course Website: ","position":{"start":{"line":10,"column":3,"offset":542},"end":{"line":10,"column":19,"offset":558}}},{"type":"element","tagName":"a","properties":{"href":"https://canvas.gatech.edu"},"children":[{"type":"text","value":"https://canvas.gatech.edu","position":{"start":{"line":10,"column":19,"offset":558},"end":{"line":10,"column":44,"offset":583}}}],"position":{"start":{"line":10,"column":19,"offset":558},"end":{"line":10,"column":44,"offset":583}}}],"position":{"start":{"line":10,"column":1,"offset":540},"end":{"line":10,"column":44,"offset":583}}},{"type":"text","value":"\n"},{"type":"element","tagName":"li","properties":{},"children":[{"type":"text","value":"Master Website: ","position":{"start":{"line":11,"column":3,"offset":586},"end":{"line":11,"column":19,"offset":602}}},{"type":"element","tagName":"a","properties":{"href":"https://gatech.instructure.com/courses/114544"},"children":[{"type":"text","value":"https://gatech.instructure.com/courses/114544","position":{"start":{"line":11,"column":19,"offset":602},"end":{"line":11,"column":64,"offset":647}}}],"position":{"start":{"line":11,"column":19,"offset":602},"end":{"line":11,"column":64,"offset":647}}}],"position":{"start":{"line":11,"column":1,"offset":584},"end":{"line":11,"column":64,"offset":647}}},{"type":"text","value":"\n"},{"type":"element","tagName":"li","properties":{},"children":[{"type":"text","value":"Course Schedule: ","position":{"start":{"line":12,"column":3,"offset":650},"end":{"line":12,"column":20,"offset":667}}},{"type":"element","tagName":"a","properties":{"href":"https://gatech.instructure.com/courses/114544/pages/spring-2023-schedule"},"children":[{"type":"text","value":"https://gatech.instructure.com/courses/114544/pages/spring-2023-schedule","position":{"start":{"line":12,"column":20,"offset":667},"end":{"line":12,"column":92,"offset":739}}}],"position":{"start":{"line":12,"column":20,"offset":667},"end":{"line":12,"column":92,"offset":739}}}],"position":{"start":{"line":12,"column":1,"offset":648},"end":{"line":12,"column":92,"offset":739}}},{"type":"text","value":"\n"}],"position":{"start":{"line":3,"column":1,"offset":24},"end":{"line":12,"column":92,"offset":739}}},{"type":"text","value":"\n"},{"type":"element","tagName":"h3","properties":{},"children":[{"type":"text","value":"Lecture slides","position":{"start":{"line":14,"column":5,"offset":745},"end":{"line":14,"column":19,"offset":759}}}],"position":{"start":{"line":14,"column":1,"offset":741},"end":{"line":14,"column":19,"offset":759}}},{"type":"text","value":"\n"},{"type":"element","tagName":"ul","properties":{},"children":[{"type":"text","value":"\n"},{"type":"element","tagName":"li","properties":{},"children":[{"type":"element","tagName":"a","properties":{"href":"https://sbarone7.math.gatech.edu/Chapters_1_and_2.pdf"},"children":[{"type":"text","value":"Chapter 1 and 2","position":{"start":{"line":15,"column":4,"offset":763},"end":{"line":15,"column":19,"offset":778}}}],"position":{"start":{"line":15,"column":3,"offset":762},"end":{"line":15,"column":75,"offset":834}}}],"position":{"start":{"line":15,"column":1,"offset":760},"end":{"line":15,"column":75,"offset":834}}},{"type":"text","value":"\n"},{"type":"element","tagName":"li","properties":{},"children":[{"type":"element","tagName":"a","properties":{"href":"https://sbarone7.math.gatech.edu/Chapters_3_thru_5.pdf"},"children":[{"type":"text","value":"Chapter 3 and 5","position":{"start":{"line":16,"column":4,"offset":838},"end":{"line":16,"column":19,"offset":853}}}],"position":{"start":{"line":16,"column":3,"offset":837},"end":{"line":16,"column":76,"offset":910}}}],"position":{"start":{"line":16,"column":1,"offset":835},"end":{"line":16,"column":76,"offset":910}}},{"type":"text","value":"\n"},{"type":"element","tagName":"li","properties":{},"children":[{"type":"element","tagName":"a","properties":{"href":"https://sbarone7.math.gatech.edu/Chapters_5_and_6.pdf"},"children":[{"type":"text","value":"Chapter 5 and 6","position":{"start":{"line":17,"column":4,"offset":914},"end":{"line":17,"column":19,"offset":929}}}],"position":{"start":{"line":17,"column":3,"offset":913},"end":{"line":17,"column":75,"offset":985}}}],"position":{"start":{"line":17,"column":1,"offset":911},"end":{"line":17,"column":75,"offset":985}}},{"type":"text","value":"\n"},{"type":"element","tagName":"li","properties":{},"children":[{"type":"element","tagName":"a","properties":{"href":"https://sbarone7.math.gatech.edu/Chapters_PageRank_and_7.pdf"},"children":[{"type":"text","value":"Chapter 7 Concepts","position":{"start":{"line":18,"column":4,"offset":989},"end":{"line":18,"column":22,"offset":1007}}}],"position":{"start":{"line":18,"column":3,"offset":988},"end":{"line":18,"column":85,"offset":1070}}}],"position":{"start":{"line":18,"column":1,"offset":986},"end":{"line":18,"column":85,"offset":1070}}},{"type":"text","value":"\n"}],"position":{"start":{"line":15,"column":1,"offset":760},"end":{"line":18,"column":85,"offset":1070}}},{"type":"text","value":"\n"},{"type":"element","tagName":"p","properties":{},"children":[{"type":"raw","value":"<b>","position":{"start":{"line":20,"column":1,"offset":1072},"end":{"line":20,"column":4,"offset":1075}}},{"type":"text","value":"Annotated Notes","position":{"start":{"line":20,"column":4,"offset":1075},"end":{"line":20,"column":19,"offset":1090}}},{"type":"raw","value":"</b>","position":{"start":{"line":20,"column":19,"offset":1090},"end":{"line":20,"column":23,"offset":1094}}},{"type":"text","value":" (Last update: 2023-01-09)","position":{"start":{"line":20,"column":23,"offset":1094},"end":{"line":20,"column":49,"offset":1120}}}],"position":{"start":{"line":20,"column":1,"offset":1072},"end":{"line":20,"column":49,"offset":1120}}},{"type":"text","value":"\n"},{"type":"element","tagName":"table","properties":{},"children":[{"type":"text","value":"\n"},{"type":"element","tagName":"thead","properties":{},"children":[{"type":"text","value":"\n"},{"type":"element","tagName":"tr","properties":{},"children":[{"type":"text","value":"\n"},{"type":"element","tagName":"th","properties":{"align":"center"},"children":[],"position":{"start":{"line":22,"column":13,"offset":1134},"end":{"line":22,"column":13,"offset":1134}}},{"type":"text","value":"\n"},{"type":"element","tagName":"th","properties":{"align":"center"},"children":[{"type":"text","value":"Chapter 1,2","position":{"start":{"line":22,"column":15,"offset":1136},"end":{"line":22,"column":26,"offset":1147}}}],"position":{"start":{"line":22,"column":15,"offset":1136},"end":{"line":22,"column":46,"offset":1167}}},{"type":"text","value":"\n"},{"type":"element","tagName":"th","properties":{"align":"center"},"children":[{"type":"text","value":"Chapter 3-5","position":{"start":{"line":22,"column":49,"offset":1170},"end":{"line":22,"column":60,"offset":1181}}}],"position":{"start":{"line":22,"column":49,"offset":1170},"end":{"line":22,"column":60,"offset":1181}}},{"type":"text","value":"\n"},{"type":"element","tagName":"th","properties":{"align":"center"},"children":[{"type":"text","value":"Chapter 5, 6","position":{"start":{"line":22,"column":63,"offset":1184},"end":{"line":22,"column":75,"offset":1196}}}],"position":{"start":{"line":22,"column":63,"offset":1184},"end":{"line":22,"column":75,"offset":1196}}},{"type":"text","value":"\n"},{"type":"element","tagName":"th","properties":{"align":"center"},"children":[{"type":"text","value":"Chapter 7 Concepts","position":{"start":{"line":22,"column":78,"offset":1199},"end":{"line":22,"column":96,"offset":1217}}}],"position":{"start":{"line":22,"column":78,"offset":1199},"end":{"line":22,"column":96,"offset":1217}}},{"type":"text","value":"\n"}],"position":{"start":{"line":22,"column":1,"offset":1122},"end":{"line":22,"column":98,"offset":1219}}},{"type":"text","value":"\n"}],"position":{"start":{"line":22,"column":1,"offset":1122},"end":{"line":22,"column":98,"offset":1219}}},{"type":"text","value":"\n"},{"type":"element","tagName":"tbody","properties":{},"children":[{"type":"text","value":"\n"},{"type":"element","tagName":"tr","properties":{},"children":[{"type":"text","value":"\n"},{"type":"element","tagName":"td","properties":{"align":"center"},"children":[{"type":"text","value":"Section A","position":{"start":{"line":24,"column":3,"offset":1320},"end":{"line":24,"column":12,"offset":1329}}}],"position":{"start":{"line":24,"column":3,"offset":1320},"end":{"line":24,"column":12,"offset":1329}}},{"type":"text","value":"\n"},{"type":"element","tagName":"td","properties":{"align":"center"},"children":[{"type":"element","tagName":"a","properties":{"href":"/7bc59406cc57fc471fd81813a7407040/secA-Chap12.pdf"},"children":[{"type":"text","value":"download","position":{"start":{"line":24,"column":16,"offset":1333},"end":{"line":24,"column":24,"offset":1341}}}],"position":{"start":{"line":24,"column":15,"offset":1332},"end":{"line":24,"column":42,"offset":1359}}}],"position":{"start":{"line":24,"column":15,"offset":1332},"end":{"line":24,"column":46,"offset":1363}}},{"type":"text","value":"\n"},{"type":"element","tagName":"td","properties":{"align":"center"},"children":[],"position":{"start":{"line":24,"column":61,"offset":1378},"end":{"line":24,"column":61,"offset":1378}}},{"type":"text","value":"\n"},{"type":"element","tagName":"td","properties":{"align":"center"},"children":[],"position":{"start":{"line":24,"column":76,"offset":1393},"end":{"line":24,"column":76,"offset":1393}}},{"type":"text","value":"\n"},{"type":"element","tagName":"td","properties":{"align":"center"},"children":[],"position":{"start":{"line":24,"column":97,"offset":1414},"end":{"line":24,"column":97,"offset":1414}}},{"type":"text","value":"\n"}],"position":{"start":{"line":24,"column":1,"offset":1318},"end":{"line":24,"column":98,"offset":1415}}},{"type":"text","value":"\n"},{"type":"element","tagName":"tr","properties":{},"children":[{"type":"text","value":"\n"},{"type":"element","tagName":"td","properties":{"align":"center"},"children":[{"type":"text","value":"Section C","position":{"start":{"line":25,"column":3,"offset":1418},"end":{"line":25,"column":12,"offset":1427}}}],"position":{"start":{"line":25,"column":3,"offset":1418},"end":{"line":25,"column":12,"offset":1427}}},{"type":"text","value":"\n"},{"type":"element","tagName":"td","properties":{"align":"center"},"children":[{"type":"element","tagName":"a","properties":{"href":"/75ba7812dd6065841a2ef8f082663d76/secC-Chap12.pdf"},"children":[{"type":"text","value":"download","position":{"start":{"line":25,"column":16,"offset":1431},"end":{"line":25,"column":24,"offset":1439}}}],"position":{"start":{"line":25,"column":15,"offset":1430},"end":{"line":25,"column":42,"offset":1457}}}],"position":{"start":{"line":25,"column":15,"offset":1430},"end":{"line":25,"column":46,"offset":1461}}},{"type":"text","value":"\n"},{"type":"element","tagName":"td","properties":{"align":"center"},"children":[],"position":{"start":{"line":25,"column":61,"offset":1476},"end":{"line":25,"column":61,"offset":1476}}},{"type":"text","value":"\n"},{"type":"element","tagName":"td","properties":{"align":"center"},"children":[],"position":{"start":{"line":25,"column":76,"offset":1491},"end":{"line":25,"column":76,"offset":1491}}},{"type":"text","value":"\n"},{"type":"element","tagName":"td","properties":{"align":"center"},"children":[],"position":{"start":{"line":25,"column":97,"offset":1512},"end":{"line":25,"column":97,"offset":1512}}},{"type":"text","value":"\n"}],"position":{"start":{"line":25,"column":1,"offset":1416},"end":{"line":25,"column":98,"offset":1513}}},{"type":"text","value":"\n"}],"position":{"start":{"line":24,"column":1,"offset":1318},"end":{"line":25,"column":98,"offset":1513}}},{"type":"text","value":"\n"}],"position":{"start":{"line":22,"column":1,"offset":1122},"end":{"line":25,"column":98,"offset":1513}}},{"type":"text","value":"\n"},{"type":"element","tagName":"h3","properties":{},"children":[{"type":"text","value":"Course Schedule","position":{"start":{"line":28,"column":5,"offset":1520},"end":{"line":28,"column":20,"offset":1535}}}],"position":{"start":{"line":28,"column":1,"offset":1516},"end":{"line":28,"column":20,"offset":1535}}},{"type":"text","value":"\n"},{"type":"element","tagName":"table","properties":{},"children":[{"type":"text","value":"\n"},{"type":"element","tagName":"thead","properties":{},"children":[{"type":"text","value":"\n"},{"type":"element","tagName":"tr","properties":{},"children":[{"type":"text","value":"\n"},{"type":"element","tagName":"th","properties":{"align":"center"},"children":[{"type":"text","value":"Week","position":{"start":{"line":29,"column":3,"offset":1538},"end":{"line":29,"column":7,"offset":1542}}}],"position":{"start":{"line":29,"column":3,"offset":1538},"end":{"line":29,"column":8,"offset":1543}}},{"type":"text","value":"\n"},{"type":"element","tagName":"th","properties":{"align":"center"},"children":[{"type":"text","value":"Date","position":{"start":{"line":29,"column":11,"offset":1546},"end":{"line":29,"column":15,"offset":1550}}}],"position":{"start":{"line":29,"column":11,"offset":1546},"end":{"line":29,"column":22,"offset":1557}}},{"type":"text","value":"\n"},{"type":"element","tagName":"th","properties":{"align":"center"},"children":[{"type":"text","value":"MON","position":{"start":{"line":29,"column":25,"offset":1560},"end":{"line":29,"column":28,"offset":1563}}}],"position":{"start":{"line":29,"column":25,"offset":1560},"end":{"line":29,"column":34,"offset":1569}}},{"type":"text","value":"\n"},{"type":"element","tagName":"th","properties":{"align":"center"},"children":[{"type":"text","value":"WED","position":{"start":{"line":29,"column":37,"offset":1572},"end":{"line":29,"column":40,"offset":1575}}}],"position":{"start":{"line":29,"column":37,"offset":1572},"end":{"line":29,"column":47,"offset":1582}}},{"type":"text","value":"\n"},{"type":"element","tagName":"th","properties":{"align":"center"},"children":[{"type":"text","value":"FRI","position":{"start":{"line":29,"column":50,"offset":1585},"end":{"line":29,"column":53,"offset":1588}}}],"position":{"start":{"line":29,"column":50,"offset":1585},"end":{"line":29,"column":55,"offset":1590}}},{"type":"text","value":"\n"}],"position":{"start":{"line":29,"column":1,"offset":1536},"end":{"line":29,"column":57,"offset":1592}}},{"type":"text","value":"\n"}],"position":{"start":{"line":29,"column":1,"offset":1536},"end":{"line":29,"column":57,"offset":1592}}},{"type":"text","value":"\n"},{"type":"element","tagName":"tbody","properties":{},"children":[{"type":"text","value":"\n"},{"type":"element","tagName":"tr","properties":{},"children":[{"type":"text","value":"\n"},{"type":"element","tagName":"td","properties":{"align":"center"},"children":[{"type":"text","value":"1","position":{"start":{"line":31,"column":3,"offset":1652},"end":{"line":31,"column":4,"offset":1653}}}],"position":{"start":{"line":31,"column":3,"offset":1652},"end":{"line":31,"column":8,"offset":1657}}},{"type":"text","value":"\n"},{"type":"element","tagName":"td","properties":{"align":"center"},"children":[{"type":"text","value":"1/9 - 1/13","position":{"start":{"line":31,"column":11,"offset":1660},"end":{"line":31,"column":21,"offset":1670}}}],"position":{"start":{"line":31,"column":11,"offset":1660},"end":{"line":31,"column":22,"offset":1671}}},{"type":"text","value":"\n"},{"type":"element","tagName":"td","properties":{"align":"center"},"children":[{"type":"text","value":"1.1","position":{"start":{"line":31,"column":25,"offset":1674},"end":{"line":31,"column":28,"offset":1677}}}],"position":{"start":{"line":31,"column":25,"offset":1674},"end":{"line":31,"column":34,"offset":1683}}},{"type":"text","value":"\n"},{"type":"element","tagName":"td","properties":{"align":"center"},"children":[{"type":"text","value":"1.2","position":{"start":{"line":31,"column":37,"offset":1686},"end":{"line":31,"column":40,"offset":1689}}}],"position":{"start":{"line":31,"column":37,"offset":1686},"end":{"line":31,"column":47,"offset":1696}}},{"type":"text","value":"\n"},{"type":"element","tagName":"td","properties":{"align":"center"},"children":[{"type":"text","value":"1.3","position":{"start":{"line":31,"column":50,"offset":1699},"end":{"line":31,"column":53,"offset":1702}}}],"position":{"start":{"line":31,"column":50,"offset":1699},"end":{"line":31,"column":55,"offset":1704}}},{"type":"text","value":"\n"}],"position":{"start":{"line":31,"column":1,"offset":1650},"end":{"line":31,"column":57,"offset":1706}}},{"type":"text","value":"\n"},{"type":"element","tagName":"tr","properties":{},"children":[{"type":"text","value":"\n"},{"type":"element","tagName":"td","properties":{"align":"center"},"children":[{"type":"text","value":"2","position":{"start":{"line":32,"column":3,"offset":1709},"end":{"line":32,"column":4,"offset":1710}}}],"position":{"start":{"line":32,"column":3,"offset":1709},"end":{"line":32,"column":8,"offset":1714}}},{"type":"text","value":"\n"},{"type":"element","tagName":"td","properties":{"align":"center"},"children":[{"type":"text","value":"1/16 - 1/20","position":{"start":{"line":32,"column":11,"offset":1717},"end":{"line":32,"column":22,"offset":1728}}}],"position":{"start":{"line":32,"column":11,"offset":1717},"end":{"line":32,"column":22,"offset":1728}}},{"type":"text","value":"\n"},{"type":"element","tagName":"td","properties":{"align":"center"},"children":[{"type":"element","tagName":"em","properties":{},"children":[{"type":"text","value":"Break","position":{"start":{"line":32,"column":26,"offset":1732},"end":{"line":32,"column":31,"offset":1737}}}],"position":{"start":{"line":32,"column":25,"offset":1731},"end":{"line":32,"column":32,"offset":1738}}}],"position":{"start":{"line":32,"column":25,"offset":1731},"end":{"line":32,"column":32,"offset":1738}}},{"type":"text","value":"\n"},{"type":"element","tagName":"td","properties":{"align":"center"},"children":[{"type":"text","value":"1.4","position":{"start":{"line":32,"column":35,"offset":1741},"end":{"line":32,"column":38,"offset":1744}}}],"position":{"start":{"line":32,"column":35,"offset":1741},"end":{"line":32,"column":45,"offset":1751}}},{"type":"text","value":"\n"},{"type":"element","tagName":"td","properties":{"align":"center"},"children":[{"type":"text","value":"1.5","position":{"start":{"line":32,"column":48,"offset":1754},"end":{"line":32,"column":51,"offset":1757}}}],"position":{"start":{"line":32,"column":48,"offset":1754},"end":{"line":32,"column":53,"offset":1759}}},{"type":"text","value":"\n"}],"position":{"start":{"line":32,"column":1,"offset":1707},"end":{"line":32,"column":55,"offset":1761}}},{"type":"text","value":"\n"},{"type":"element","tagName":"tr","properties":{},"children":[{"type":"text","value":"\n"},{"type":"element","tagName":"td","properties":{"align":"center"},"children":[{"type":"text","value":"3","position":{"start":{"line":33,"column":3,"offset":1764},"end":{"line":33,"column":4,"offset":1765}}}],"position":{"start":{"line":33,"column":3,"offset":1764},"end":{"line":33,"column":8,"offset":1769}}},{"type":"text","value":"\n"},{"type":"element","tagName":"td","properties":{"align":"center"},"children":[{"type":"text","value":"1/23 - 1/27","position":{"start":{"line":33,"column":11,"offset":1772},"end":{"line":33,"column":22,"offset":1783}}}],"position":{"start":{"line":33,"column":11,"offset":1772},"end":{"line":33,"column":22,"offset":1783}}},{"type":"text","value":"\n"},{"type":"element","tagName":"td","properties":{"align":"center"},"children":[{"type":"text","value":"1.7","position":{"start":{"line":33,"column":25,"offset":1786},"end":{"line":33,"column":28,"offset":1789}}}],"position":{"start":{"line":33,"column":25,"offset":1786},"end":{"line":33,"column":34,"offset":1795}}},{"type":"text","value":"\n"},{"type":"element","tagName":"td","properties":{"align":"center"},"children":[{"type":"text","value":"1.8","position":{"start":{"line":33,"column":37,"offset":1798},"end":{"line":33,"column":40,"offset":1801}}}],"position":{"start":{"line":33,"column":37,"offset":1798},"end":{"line":33,"column":47,"offset":1808}}},{"type":"text","value":"\n"},{"type":"element","tagName":"td","properties":{"align":"center"},"children":[{"type":"text","value":"1.9","position":{"start":{"line":33,"column":50,"offset":1811},"end":{"line":33,"column":53,"offset":1814}}}],"position":{"start":{"line":33,"column":50,"offset":1811},"end":{"line":33,"column":55,"offset":1816}}},{"type":"text","value":"\n"}],"position":{"start":{"line":33,"column":1,"offset":1762},"end":{"line":33,"column":57,"offset":1818}}},{"type":"text","value":"\n"},{"type":"element","tagName":"tr","properties":{},"children":[{"type":"text","value":"\n"},{"type":"element","tagName":"td","properties":{"align":"center"},"children":[{"type":"text","value":"4","position":{"start":{"line":34,"column":3,"offset":1821},"end":{"line":34,"column":4,"offset":1822}}}],"position":{"start":{"line":34,"column":3,"offset":1821},"end":{"line":34,"column":8,"offset":1826}}},{"type":"text","value":"\n"},{"type":"element","tagName":"td","properties":{"align":"center"},"children":[{"type":"text","value":"1/30 - 2/3","position":{"start":{"line":34,"column":11,"offset":1829},"end":{"line":34,"column":21,"offset":1839}}}],"position":{"start":{"line":34,"column":11,"offset":1829},"end":{"line":34,"column":22,"offset":1840}}},{"type":"text","value":"\n"},{"type":"element","tagName":"td","properties":{"align":"center"},"children":[{"type":"text","value":"1.9,2.1","position":{"start":{"line":34,"column":25,"offset":1843},"end":{"line":34,"column":32,"offset":1850}}}],"position":{"start":{"line":34,"column":25,"offset":1843},"end":{"line":34,"column":34,"offset":1852}}},{"type":"text","value":"\n"},{"type":"element","tagName":"td","properties":{"align":"center"},"children":[{"type":"element","tagName":"strong","properties":{},"children":[{"type":"text","value":"Exam 1","position":{"start":{"line":34,"column":39,"offset":1857},"end":{"line":34,"column":45,"offset":1863}}}],"position":{"start":{"line":34,"column":37,"offset":1855},"end":{"line":34,"column":47,"offset":1865}}}],"position":{"start":{"line":34,"column":37,"offset":1855},"end":{"line":34,"column":47,"offset":1865}}},{"type":"text","value":"\n"},{"type":"element","tagName":"td","properties":{"align":"center"},"children":[{"type":"text","value":"2.2","position":{"start":{"line":34,"column":50,"offset":1868},"end":{"line":34,"column":53,"offset":1871}}}],"position":{"start":{"line":34,"column":50,"offset":1868},"end":{"line":34,"column":55,"offset":1873}}},{"type":"text","value":"\n"}],"position":{"start":{"line":34,"column":1,"offset":1819},"end":{"line":34,"column":57,"offset":1875}}},{"type":"text","value":"\n"},{"type":"element","tagName":"tr","properties":{},"children":[{"type":"text","value":"\n"},{"type":"element","tagName":"td","properties":{"align":"center"},"children":[{"type":"text","value":"5","position":{"start":{"line":35,"column":3,"offset":1878},"end":{"line":35,"column":4,"offset":1879}}}],"position":{"start":{"line":35,"column":3,"offset":1878},"end":{"line":35,"column":8,"offset":1883}}},{"type":"text","value":"\n"},{"type":"element","tagName":"td","properties":{"align":"center"},"children":[{"type":"text","value":"2/6 - 2/10","position":{"start":{"line":35,"column":11,"offset":1886},"end":{"line":35,"column":21,"offset":1896}}}],"position":{"start":{"line":35,"column":11,"offset":1886},"end":{"line":35,"column":22,"offset":1897}}},{"type":"text","value":"\n"},{"type":"element","tagName":"td","properties":{"align":"center"},"children":[{"type":"text","value":"2.3,4","position":{"start":{"line":35,"column":25,"offset":1900},"end":{"line":35,"column":30,"offset":1905}}}],"position":{"start":{"line":35,"column":25,"offset":1900},"end":{"line":35,"column":34,"offset":1909}}},{"type":"text","value":"\n"},{"type":"element","tagName":"td","properties":{"align":"center"},"children":[{"type":"text","value":"2.5","position":{"start":{"line":35,"column":37,"offset":1912},"end":{"line":35,"column":40,"offset":1915}}}],"position":{"start":{"line":35,"column":37,"offset":1912},"end":{"line":35,"column":47,"offset":1922}}},{"type":"text","value":"\n"},{"type":"element","tagName":"td","properties":{"align":"center"},"children":[{"type":"text","value":"2.8","position":{"start":{"line":35,"column":50,"offset":1925},"end":{"line":35,"column":53,"offset":1928}}}],"position":{"start":{"line":35,"column":50,"offset":1925},"end":{"line":35,"column":55,"offset":1930}}},{"type":"text","value":"\n"}],"position":{"start":{"line":35,"column":1,"offset":1876},"end":{"line":35,"column":57,"offset":1932}}},{"type":"text","value":"\n"},{"type":"element","tagName":"tr","properties":{},"children":[{"type":"text","value":"\n"},{"type":"element","tagName":"td","properties":{"align":"center"},"children":[{"type":"text","value":"6","position":{"start":{"line":36,"column":3,"offset":1935},"end":{"line":36,"column":4,"offset":1936}}}],"position":{"start":{"line":36,"column":3,"offset":1935},"end":{"line":36,"column":8,"offset":1940}}},{"type":"text","value":"\n"},{"type":"element","tagName":"td","properties":{"align":"center"},"children":[{"type":"text","value":"2/13 - 2/17","position":{"start":{"line":36,"column":11,"offset":1943},"end":{"line":36,"column":22,"offset":1954}}}],"position":{"start":{"line":36,"column":11,"offset":1943},"end":{"line":36,"column":22,"offset":1954}}},{"type":"text","value":"\n"},{"type":"element","tagName":"td","properties":{"align":"center"},"children":[{"type":"text","value":"2.9","position":{"start":{"line":36,"column":25,"offset":1957},"end":{"line":36,"column":28,"offset":1960}}}],"position":{"start":{"line":36,"column":25,"offset":1957},"end":{"line":36,"column":34,"offset":1966}}},{"type":"text","value":"\n"},{"type":"element","tagName":"td","properties":{"align":"center"},"children":[{"type":"text","value":"2.9,3.1","position":{"start":{"line":36,"column":37,"offset":1969},"end":{"line":36,"column":44,"offset":1976}}}],"position":{"start":{"line":36,"column":37,"offset":1969},"end":{"line":36,"column":47,"offset":1979}}},{"type":"text","value":"\n"},{"type":"element","tagName":"td","properties":{"align":"center"},"children":[{"type":"text","value":"3.2","position":{"start":{"line":36,"column":50,"offset":1982},"end":{"line":36,"column":53,"offset":1985}}}],"position":{"start":{"line":36,"column":50,"offset":1982},"end":{"line":36,"column":55,"offset":1987}}},{"type":"text","value":"\n"}],"position":{"start":{"line":36,"column":1,"offset":1933},"end":{"line":36,"column":57,"offset":1989}}},{"type":"text","value":"\n"},{"type":"element","tagName":"tr","properties":{},"children":[{"type":"text","value":"\n"},{"type":"element","tagName":"td","properties":{"align":"center"},"children":[{"type":"text","value":"7","position":{"start":{"line":37,"column":3,"offset":1992},"end":{"line":37,"column":4,"offset":1993}}}],"position":{"start":{"line":37,"column":3,"offset":1992},"end":{"line":37,"column":8,"offset":1997}}},{"type":"text","value":"\n"},{"type":"element","tagName":"td","properties":{"align":"center"},"children":[{"type":"text","value":"2/20 - 2/24","position":{"start":{"line":37,"column":11,"offset":2000},"end":{"line":37,"column":22,"offset":2011}}}],"position":{"start":{"line":37,"column":11,"offset":2000},"end":{"line":37,"column":22,"offset":2011}}},{"type":"text","value":"\n"},{"type":"element","tagName":"td","properties":{"align":"center"},"children":[{"type":"text","value":"3.3","position":{"start":{"line":37,"column":25,"offset":2014},"end":{"line":37,"column":28,"offset":2017}}}],"position":{"start":{"line":37,"column":25,"offset":2014},"end":{"line":37,"column":34,"offset":2023}}},{"type":"text","value":"\n"},{"type":"element","tagName":"td","properties":{"align":"center"},"children":[{"type":"text","value":"4.9","position":{"start":{"line":37,"column":37,"offset":2026},"end":{"line":37,"column":40,"offset":2029}}}],"position":{"start":{"line":37,"column":37,"offset":2026},"end":{"line":37,"column":47,"offset":2036}}},{"type":"text","value":"\n"},{"type":"element","tagName":"td","properties":{"align":"center"},"children":[{"type":"text","value":"5.1","position":{"start":{"line":37,"column":50,"offset":2039},"end":{"line":37,"column":53,"offset":2042}}}],"position":{"start":{"line":37,"column":50,"offset":2039},"end":{"line":37,"column":55,"offset":2044}}},{"type":"text","value":"\n"}],"position":{"start":{"line":37,"column":1,"offset":1990},"end":{"line":37,"column":57,"offset":2046}}},{"type":"text","value":"\n"},{"type":"element","tagName":"tr","properties":{},"children":[{"type":"text","value":"\n"},{"type":"element","tagName":"td","properties":{"align":"center"},"children":[{"type":"text","value":"8","position":{"start":{"line":38,"column":3,"offset":2049},"end":{"line":38,"column":4,"offset":2050}}}],"position":{"start":{"line":38,"column":3,"offset":2049},"end":{"line":38,"column":8,"offset":2054}}},{"type":"text","value":"\n"},{"type":"element","tagName":"td","properties":{"align":"center"},"children":[{"type":"text","value":"2/27 - 3/3","position":{"start":{"line":38,"column":11,"offset":2057},"end":{"line":38,"column":21,"offset":2067}}}],"position":{"start":{"line":38,"column":11,"offset":2057},"end":{"line":38,"column":22,"offset":2068}}},{"type":"text","value":"\n"},{"type":"element","tagName":"td","properties":{"align":"center"},"children":[{"type":"text","value":"5.2","position":{"start":{"line":38,"column":25,"offset":2071},"end":{"line":38,"column":28,"offset":2074}}}],"position":{"start":{"line":38,"column":25,"offset":2071},"end":{"line":38,"column":34,"offset":2080}}},{"type":"text","value":"\n"},{"type":"element","tagName":"td","properties":{"align":"center"},"children":[{"type":"element","tagName":"strong","properties":{},"children":[{"type":"text","value":"Exam 2","position":{"start":{"line":38,"column":39,"offset":2085},"end":{"line":38,"column":45,"offset":2091}}}],"position":{"start":{"line":38,"column":37,"offset":2083},"end":{"line":38,"column":47,"offset":2093}}}],"position":{"start":{"line":38,"column":37,"offset":2083},"end":{"line":38,"column":47,"offset":2093}}},{"type":"text","value":"\n"},{"type":"element","tagName":"td","properties":{"align":"center"},"children":[],"position":{"start":{"line":38,"column":56,"offset":2102},"end":{"line":38,"column":56,"offset":2102}}},{"type":"text","value":"\n"}],"position":{"start":{"line":38,"column":1,"offset":2047},"end":{"line":38,"column":57,"offset":2103}}},{"type":"text","value":"\n"},{"type":"element","tagName":"tr","properties":{},"children":[{"type":"text","value":"\n"},{"type":"element","tagName":"td","properties":{"align":"center"},"children":[{"type":"text","value":"9","position":{"start":{"line":39,"column":3,"offset":2106},"end":{"line":39,"column":4,"offset":2107}}}],"position":{"start":{"line":39,"column":3,"offset":2106},"end":{"line":39,"column":8,"offset":2111}}},{"type":"text","value":"\n"},{"type":"element","tagName":"td","properties":{"align":"center"},"children":[{"type":"text","value":"3/6 - 3/10","position":{"start":{"line":39,"column":11,"offset":2114},"end":{"line":39,"column":21,"offset":2124}}}],"position":{"start":{"line":39,"column":11,"offset":2114},"end":{"line":39,"column":22,"offset":2125}}},{"type":"text","value":"\n"},{"type":"element","tagName":"td","properties":{"align":"center"},"children":[],"position":{"start":{"line":39,"column":35,"offset":2138},"end":{"line":39,"column":35,"offset":2138}}},{"type":"text","value":"\n"},{"type":"element","tagName":"td","properties":{"align":"center"},"children":[],"position":{"start":{"line":39,"column":48,"offset":2151},"end":{"line":39,"column":48,"offset":2151}}},{"type":"text","value":"\n"},{"type":"element","tagName":"td","properties":{"align":"center"},"children":[],"position":{"start":{"line":39,"column":56,"offset":2159},"end":{"line":39,"column":56,"offset":2159}}},{"type":"text","value":"\n"}],"position":{"start":{"line":39,"column":1,"offset":2104},"end":{"line":39,"column":57,"offset":2160}}},{"type":"text","value":"\n"},{"type":"element","tagName":"tr","properties":{},"children":[{"type":"text","value":"\n"},{"type":"element","tagName":"td","properties":{"align":"center"},"children":[{"type":"text","value":"10","position":{"start":{"line":40,"column":3,"offset":2163},"end":{"line":40,"column":5,"offset":2165}}}],"position":{"start":{"line":40,"column":3,"offset":2163},"end":{"line":40,"column":8,"offset":2168}}},{"type":"text","value":"\n"},{"type":"element","tagName":"td","properties":{"align":"center"},"children":[{"type":"text","value":"3/13 - 3/17","position":{"start":{"line":40,"column":11,"offset":2171},"end":{"line":40,"column":22,"offset":2182}}}],"position":{"start":{"line":40,"column":11,"offset":2171},"end":{"line":40,"column":22,"offset":2182}}},{"type":"text","value":"\n"},{"type":"element","tagName":"td","properties":{"align":"center"},"children":[],"position":{"start":{"line":40,"column":35,"offset":2195},"end":{"line":40,"column":35,"offset":2195}}},{"type":"text","value":"\n"},{"type":"element","tagName":"td","properties":{"align":"center"},"children":[],"position":{"start":{"line":40,"column":48,"offset":2208},"end":{"line":40,"column":48,"offset":2208}}},{"type":"text","value":"\n"},{"type":"element","tagName":"td","properties":{"align":"center"},"children":[],"position":{"start":{"line":40,"column":56,"offset":2216},"end":{"line":40,"column":56,"offset":2216}}},{"type":"text","value":"\n"}],"position":{"start":{"line":40,"column":1,"offset":2161},"end":{"line":40,"column":57,"offset":2217}}},{"type":"text","value":"\n"},{"type":"element","tagName":"tr","properties":{},"children":[{"type":"text","value":"\n"},{"type":"element","tagName":"td","properties":{"align":"center"},"children":[{"type":"text","value":"11","position":{"start":{"line":41,"column":3,"offset":2220},"end":{"line":41,"column":5,"offset":2222}}}],"position":{"start":{"line":41,"column":3,"offset":2220},"end":{"line":41,"column":8,"offset":2225}}},{"type":"text","value":"\n"},{"type":"element","tagName":"td","properties":{"align":"center"},"children":[{"type":"text","value":"3/20 - 3/24","position":{"start":{"line":41,"column":11,"offset":2228},"end":{"line":41,"column":22,"offset":2239}}}],"position":{"start":{"line":41,"column":11,"offset":2228},"end":{"line":41,"column":22,"offset":2239}}},{"type":"text","value":"\n"},{"type":"element","tagName":"td","properties":{"align":"center"},"children":[],"position":{"start":{"line":41,"column":35,"offset":2252},"end":{"line":41,"column":35,"offset":2252}}},{"type":"text","value":"\n"},{"type":"element","tagName":"td","properties":{"align":"center"},"children":[],"position":{"start":{"line":41,"column":48,"offset":2265},"end":{"line":41,"column":48,"offset":2265}}},{"type":"text","value":"\n"},{"type":"element","tagName":"td","properties":{"align":"center"},"children":[],"position":{"start":{"line":41,"column":56,"offset":2273},"end":{"line":41,"column":56,"offset":2273}}},{"type":"text","value":"\n"}],"position":{"start":{"line":41,"column":1,"offset":2218},"end":{"line":41,"column":57,"offset":2274}}},{"type":"text","value":"\n"},{"type":"element","tagName":"tr","properties":{},"children":[{"type":"text","value":"\n"},{"type":"element","tagName":"td","properties":{"align":"center"},"children":[{"type":"text","value":"12","position":{"start":{"line":42,"column":3,"offset":2277},"end":{"line":42,"column":5,"offset":2279}}}],"position":{"start":{"line":42,"column":3,"offset":2277},"end":{"line":42,"column":8,"offset":2282}}},{"type":"text","value":"\n"},{"type":"element","tagName":"td","properties":{"align":"center"},"children":[{"type":"text","value":"3/27 - 3/31","position":{"start":{"line":42,"column":11,"offset":2285},"end":{"line":42,"column":22,"offset":2296}}}],"position":{"start":{"line":42,"column":11,"offset":2285},"end":{"line":42,"column":22,"offset":2296}}},{"type":"text","value":"\n"},{"type":"element","tagName":"td","properties":{"align":"center"},"children":[],"position":{"start":{"line":42,"column":35,"offset":2309},"end":{"line":42,"column":35,"offset":2309}}},{"type":"text","value":"\n"},{"type":"element","tagName":"td","properties":{"align":"center"},"children":[],"position":{"start":{"line":42,"column":48,"offset":2322},"end":{"line":42,"column":48,"offset":2322}}},{"type":"text","value":"\n"},{"type":"element","tagName":"td","properties":{"align":"center"},"children":[],"position":{"start":{"line":42,"column":56,"offset":2330},"end":{"line":42,"column":56,"offset":2330}}},{"type":"text","value":"\n"}],"position":{"start":{"line":42,"column":1,"offset":2275},"end":{"line":42,"column":57,"offset":2331}}},{"type":"text","value":"\n"},{"type":"element","tagName":"tr","properties":{},"children":[{"type":"text","value":"\n"},{"type":"element","tagName":"td","properties":{"align":"center"},"children":[{"type":"text","value":"13","position":{"start":{"line":43,"column":3,"offset":2334},"end":{"line":43,"column":5,"offset":2336}}}],"position":{"start":{"line":43,"column":3,"offset":2334},"end":{"line":43,"column":8,"offset":2339}}},{"type":"text","value":"\n"},{"type":"element","tagName":"td","properties":{"align":"center"},"children":[{"type":"text","value":"4/3 - 4/7","position":{"start":{"line":43,"column":11,"offset":2342},"end":{"line":43,"column":20,"offset":2351}}}],"position":{"start":{"line":43,"column":11,"offset":2342},"end":{"line":43,"column":22,"offset":2353}}},{"type":"text","value":"\n"},{"type":"element","tagName":"td","properties":{"align":"center"},"children":[],"position":{"start":{"line":43,"column":35,"offset":2366},"end":{"line":43,"column":35,"offset":2366}}},{"type":"text","value":"\n"},{"type":"element","tagName":"td","properties":{"align":"center"},"children":[],"position":{"start":{"line":43,"column":48,"offset":2379},"end":{"line":43,"column":48,"offset":2379}}},{"type":"text","value":"\n"},{"type":"element","tagName":"td","properties":{"align":"center"},"children":[],"position":{"start":{"line":43,"column":56,"offset":2387},"end":{"line":43,"column":56,"offset":2387}}},{"type":"text","value":"\n"}],"position":{"start":{"line":43,"column":1,"offset":2332},"end":{"line":43,"column":57,"offset":2388}}},{"type":"text","value":"\n"},{"type":"element","tagName":"tr","properties":{},"children":[{"type":"text","value":"\n"},{"type":"element","tagName":"td","properties":{"align":"center"},"children":[{"type":"text","value":"14","position":{"start":{"line":44,"column":3,"offset":2391},"end":{"line":44,"column":5,"offset":2393}}}],"position":{"start":{"line":44,"column":3,"offset":2391},"end":{"line":44,"column":8,"offset":2396}}},{"type":"text","value":"\n"},{"type":"element","tagName":"td","properties":{"align":"center"},"children":[{"type":"text","value":"4/10 - 4/14","position":{"start":{"line":44,"column":11,"offset":2399},"end":{"line":44,"column":22,"offset":2410}}}],"position":{"start":{"line":44,"column":11,"offset":2399},"end":{"line":44,"column":22,"offset":2410}}},{"type":"text","value":"\n"},{"type":"element","tagName":"td","properties":{"align":"center"},"children":[],"position":{"start":{"line":44,"column":35,"offset":2423},"end":{"line":44,"column":35,"offset":2423}}},{"type":"text","value":"\n"},{"type":"element","tagName":"td","properties":{"align":"center"},"children":[],"position":{"start":{"line":44,"column":48,"offset":2436},"end":{"line":44,"column":48,"offset":2436}}},{"type":"text","value":"\n"},{"type":"element","tagName":"td","properties":{"align":"center"},"children":[],"position":{"start":{"line":44,"column":56,"offset":2444},"end":{"line":44,"column":56,"offset":2444}}},{"type":"text","value":"\n"}],"position":{"start":{"line":44,"column":1,"offset":2389},"end":{"line":44,"column":57,"offset":2445}}},{"type":"text","value":"\n"},{"type":"element","tagName":"tr","properties":{},"children":[{"type":"text","value":"\n"},{"type":"element","tagName":"td","properties":{"align":"center"},"children":[{"type":"text","value":"15","position":{"start":{"line":45,"column":3,"offset":2448},"end":{"line":45,"column":5,"offset":2450}}}],"position":{"start":{"line":45,"column":3,"offset":2448},"end":{"line":45,"column":8,"offset":2453}}},{"type":"text","value":"\n"},{"type":"element","tagName":"td","properties":{"align":"center"},"children":[{"type":"text","value":"4/17 - 4/21","position":{"start":{"line":45,"column":11,"offset":2456},"end":{"line":45,"column":22,"offset":2467}}}],"position":{"start":{"line":45,"column":11,"offset":2456},"end":{"line":45,"column":22,"offset":2467}}},{"type":"text","value":"\n"},{"type":"element","tagName":"td","properties":{"align":"center"},"children":[],"position":{"start":{"line":45,"column":35,"offset":2480},"end":{"line":45,"column":35,"offset":2480}}},{"type":"text","value":"\n"},{"type":"element","tagName":"td","properties":{"align":"center"},"children":[],"position":{"start":{"line":45,"column":48,"offset":2493},"end":{"line":45,"column":48,"offset":2493}}},{"type":"text","value":"\n"},{"type":"element","tagName":"td","properties":{"align":"center"},"children":[],"position":{"start":{"line":45,"column":56,"offset":2501},"end":{"line":45,"column":56,"offset":2501}}},{"type":"text","value":"\n"}],"position":{"start":{"line":45,"column":1,"offset":2446},"end":{"line":45,"column":57,"offset":2502}}},{"type":"text","value":"\n"},{"type":"element","tagName":"tr","properties":{},"children":[{"type":"text","value":"\n"},{"type":"element","tagName":"td","properties":{"align":"center"},"children":[{"type":"text","value":"16","position":{"start":{"line":46,"column":3,"offset":2505},"end":{"line":46,"column":5,"offset":2507}}}],"position":{"start":{"line":46,"column":3,"offset":2505},"end":{"line":46,"column":8,"offset":2510}}},{"type":"text","value":"\n"},{"type":"element","tagName":"td","properties":{"align":"center"},"children":[{"type":"text","value":"4/24 - 4/28","position":{"start":{"line":46,"column":11,"offset":2513},"end":{"line":46,"column":22,"offset":2524}}}],"position":{"start":{"line":46,"column":11,"offset":2513},"end":{"line":46,"column":22,"offset":2524}}},{"type":"text","value":"\n"},{"type":"element","tagName":"td","properties":{"align":"center"},"children":[],"position":{"start":{"line":46,"column":35,"offset":2537},"end":{"line":46,"column":35,"offset":2537}}},{"type":"text","value":"\n"},{"type":"element","tagName":"td","properties":{"align":"center"},"children":[],"position":{"start":{"line":46,"column":48,"offset":2550},"end":{"line":46,"column":48,"offset":2550}}},{"type":"text","value":"\n"},{"type":"element","tagName":"td","properties":{"align":"center"},"children":[],"position":{"start":{"line":46,"column":56,"offset":2558},"end":{"line":46,"column":56,"offset":2558}}},{"type":"text","value":"\n"}],"position":{"start":{"line":46,"column":1,"offset":2503},"end":{"line":46,"column":57,"offset":2559}}},{"type":"text","value":"\n"},{"type":"element","tagName":"tr","properties":{},"children":[{"type":"text","value":"\n"},{"type":"element","tagName":"td","properties":{"align":"center"},"children":[{"type":"text","value":"17","position":{"start":{"line":47,"column":3,"offset":2562},"end":{"line":47,"column":5,"offset":2564}}}],"position":{"start":{"line":47,"column":3,"offset":2562},"end":{"line":47,"column":8,"offset":2567}}},{"type":"text","value":"\n"},{"type":"element","tagName":"td","properties":{"align":"center"},"children":[{"type":"text","value":"5/1 - 5/4","position":{"start":{"line":47,"column":11,"offset":2570},"end":{"line":47,"column":20,"offset":2579}}}],"position":{"start":{"line":47,"column":11,"offset":2570},"end":{"line":47,"column":22,"offset":2581}}},{"type":"text","value":"\n"},{"type":"element","tagName":"td","properties":{"align":"center"},"children":[],"position":{"start":{"line":47,"column":35,"offset":2594},"end":{"line":47,"column":35,"offset":2594}}},{"type":"text","value":"\n"},{"type":"element","tagName":"td","properties":{"align":"center"},"children":[],"position":{"start":{"line":47,"column":48,"offset":2607},"end":{"line":47,"column":48,"offset":2607}}},{"type":"text","value":"\n"},{"type":"element","tagName":"td","properties":{"align":"center"},"children":[],"position":{"start":{"line":47,"column":56,"offset":2615},"end":{"line":47,"column":56,"offset":2615}}},{"type":"text","value":"\n"}],"position":{"start":{"line":47,"column":1,"offset":2560},"end":{"line":47,"column":57,"offset":2616}}},{"type":"text","value":"\n"}],"position":{"start":{"line":31,"column":1,"offset":1650},"end":{"line":47,"column":57,"offset":2616}}},{"type":"text","value":"\n"}],"position":{"start":{"line":29,"column":1,"offset":1536},"end":{"line":47,"column":57,"offset":2616}}},{"type":"text","value":"\n"},{"type":"raw","value":"<!--\n| Week | Date        | M         | T          | W          | R             | F   |\n| ---  | ---         | ---       | ---        | ---        | ---           | --- |\n| 1    | 1/9 - 1/13  | 1.1       | WS 1.1     | 1.2        | WS 1.2        | 1.3 |\n| 2    | 1/16 - 1/20 | **Break** | WS 1.3     | 1.4        | WS 1.4        | 1.5 |\n| 3    | 1/23 - 1/27 | 1.7       | WS 1.5,7   | 1.8        | WS 1.8        | 1.9 |\n| 4    | 1/30 - 2/3  | 1.9,2.1   | WS 1.9,2.1 | **Exam 1** | **Cancelled** | 2.2 |\n| 5    | 2/6 - 2/10  | 2.3,4     | WS 2.2-4   | 2.5        | WS 2.5        | 2.8 |\n| 6    | 2/13 - 2/17 | 2.9       | WS 2.8     | 2.9,3.1    | WS 2.9,3.1    | 3.2 |\n| 7    | 2/20 - 2/24 | 3.3       | WS 3.2     | 4.9        | WS 3.3,4.9    | 5.1 |\n| 8    | 2/27 - 3/3  | 5.2       | WS 5.1,2   | **Exam 2** | WS            |     |\n| 9    | 3/6 - 3/10  |           | WS         |            | WS            |     |\n| 10   | 3/13 - 3/17 |           | WS         |            | WS            |     |\n| 11   | 3/20 - 3/24 |           | WS         |            | WS            |     |\n| 12   | 3/27 - 3/31 |           | WS         |            | WS            |     |\n| 13   | 4/3 - 4/7   |           | WS         |            | WS            |     |\n| 14   | 4/10 - 4/14 |           | WS         |            | WS            |     |\n| 15   | 4/17 - 4/21 |           | WS         |            | WS            |     |\n| 16   | 4/24 - 4/28 |           | WS         |            | WS            |     |\n| 17   | 5/1 - 5/4   |           | WS         |            | WS            |     |\n-->","position":{"start":{"line":48,"column":1,"offset":2617},"end":{"line":68,"column":4,"offset":4202}}},{"type":"text","value":"\n"},{"type":"raw","value":"<style>\ntable, th, td {\n  border: 1px solid #eee;\n  border-collapse: collapse;\n}\n</style>","position":{"start":{"line":69,"column":1,"offset":4203},"end":{"line":74,"column":9,"offset":4292}}}],"position":{"start":{"line":1,"column":1,"offset":0},"end":{"line":76,"column":1,"offset":4294}}}}